eventlet/__init__.py
eventlet/backdoor.py
eventlet/convenience.py
eventlet/corolocal.py
eventlet/coros.py
eventlet/dagpool.py
eventlet/db_pool.py
eventlet/debug.py
eventlet/event.py
eventlet/greenpool.py
eventlet/greenthread.py
eventlet/lock.py
eventlet/patcher.py
eventlet/pools.py
eventlet/queue.py
eventlet/semaphore.py
eventlet/timeout.py
eventlet/tpool.py
eventlet/websocket.py
eventlet/wsgi.py
eventlet/green/BaseHTTPServer.py
eventlet/green/CGIHTTPServer.py
eventlet/green/MySQLdb.py
eventlet/green/Queue.py
eventlet/green/SimpleHTTPServer.py
eventlet/green/SocketServer.py
eventlet/green/__init__.py
eventlet/green/_socket_nodns.py
eventlet/green/asynchat.py
eventlet/green/asyncore.py
eventlet/green/builtin.py
eventlet/green/ftplib.py
eventlet/green/httplib.py
eventlet/green/os.py
eventlet/green/profile.py
eventlet/green/select.py
eventlet/green/selectors.py
eventlet/green/socket.py
eventlet/green/ssl.py
eventlet/green/subprocess.py
eventlet/green/thread.py
eventlet/green/threading.py
eventlet/green/time.py
eventlet/green/urllib2.py
eventlet/green/zmq.py
eventlet/green/OpenSSL/SSL.py
eventlet/green/OpenSSL/__init__.py
eventlet/green/OpenSSL/crypto.py
eventlet/green/OpenSSL/tsafe.py
eventlet/green/OpenSSL/version.py
eventlet/green/http/__init__.py
eventlet/green/http/client.py
eventlet/green/http/cookiejar.py
eventlet/green/http/cookies.py
eventlet/green/http/server.py
eventlet/green/urllib/__init__.py
eventlet/green/urllib/error.py
eventlet/green/urllib/parse.py
eventlet/green/urllib/request.py
eventlet/green/urllib/response.py
eventlet/greenio/__init__.py
eventlet/greenio/base.py
eventlet/greenio/py2.py
eventlet/greenio/py3.py
eventlet/hubs/__init__.py
eventlet/hubs/epolls.py
eventlet/hubs/hub.py
eventlet/hubs/kqueue.py
eventlet/hubs/poll.py
eventlet/hubs/pyevent.py
eventlet/hubs/selects.py
eventlet/hubs/timer.py
eventlet/support/__init__.py
eventlet/support/greendns.py
eventlet/support/greenlets.py
eventlet/support/psycopg2_patcher.py
eventlet/support/pylib.py
eventlet-0.33.2.dist-info/AUTHORS
eventlet-0.33.2.dist-info/LICENSE
eventlet-0.33.2.dist-info/METADATA
eventlet-0.33.2.dist-info/WHEEL
eventlet-0.33.2.dist-info/top_level.txt
eventlet-0.33.2.dist-info/RECORD
